aws_lambda_sample_events/__init__.py
aws_lambda_sample_events/sample_event.py
aws_lambda_sample_events/unknown_service_error.py
aws_lambda_sample_events/json_samples/cloudformation.json
aws_lambda_sample_events/json_samples/cloudwatch_events.json
aws_lambda_sample_events/json_samples/cloudwatch_logs.json
aws_lambda_sample_events/json_samples/codepipeline.json
aws_lambda_sample_events/json_samples/cognito_sync_trigger.json
aws_lambda_sample_events/json_samples/config_rule.json
aws_lambda_sample_events/json_samples/dynamodb_update.json
aws_lambda_sample_events/json_samples/kinesis_stream.json
aws_lambda_sample_events/json_samples/s3_delete.json
aws_lambda_sample_events/json_samples/s3_put.json
aws_lambda_sample_events/json_samples/scheduled.json
aws_lambda_sample_events/json_samples/ses.json
aws_lambda_sample_events/json_samples/sns.json
aws_lambda_sample_events-1.0.1.dist-info/DESCRIPTION.rst
aws_lambda_sample_events-1.0.1.dist-info/METADATA
aws_lambda_sample_events-1.0.1.dist-info/RECORD
aws_lambda_sample_events-1.0.1.dist-info/WHEEL
aws_lambda_sample_events-1.0.1.dist-info/metadata.json
aws_lambda_sample_events-1.0.1.dist-info/top_level.txt
