Metadata-Version: 2.0
Name: aws-lambda-sample-events
Version: 1.0.1
Summary: A Python module for creating sample events to test AWS Lambda functions.
Home-page: https://github.com/awslabs/aws_lambda_sample_events_python
Author: Josh Campbell
Author-email: joshcb@amazon.com
License: Apache 2.0
Keywords: aws,lambda
Platform: UNKNOWN
Classifier: Development Status :: 4 - Beta
Classifier: Intended Audience :: Developers
Classifier: License :: OSI Approved :: Apache Software License
Classifier: Operating System :: POSIX
Classifier: Programming Language :: Python
Classifier: Topic :: Software Development :: Libraries :: Python Modules
